{"created_at": "Fri Sep 18 11:27:39 +0000 2020", "id": 1306917797939884032, "id_str": "1306917797939884032", "text": "$U priced its IPO of 25M shares at $52 (above the expected price range of $44-48 which was already raised from $34-\u2026 https://t.co/DZ0fDZu6YP", "source": "<a href=\"https://mobile.twitter.com\" rel=\"nofollow\">Twitter Web App</a>", "truncated": true, "in_reply_to_status_id": null, "in_reply_to_status_id_str": null, "in_reply_to_user_id": null, "in_reply_to_user_id_str": null, "in_reply_to_screen_name": null, "user": {"id": 1098642312614297600, "id_str": "1098642312614297600", "name": "TraderJEB", "screen_name": "TraderJEB", "location": "New York, USA", "url": null, "description": "I tweet about stocks (personal opinions; not investment advice), politics, and Liverpool FC.", "translator_type": "none", "protected": false, "verified": false, "followers_count": 12, "friends_count": 145, "listed_count": 0, "favourites_count": 424, "statuses_count": 273, "created_at": "Thu Feb 21 17:55:13 +0000 2019", "utc_offset": null, "time_zone": null, "geo_enabled": false, "lang": null, "contributors_enabled": false, "is_translator": false, "profile_background_color": "000000", "profile_background_image_url": "http://abs.twimg.com/images/themes/theme1/bg.png", "profile_background_image_url_https": "https://abs.twimg.com/images/themes/theme1/bg.png", "profile_background_tile": false, "profile_link_color": "1B95E0", "profile_sidebar_border_color": "000000", "profile_sidebar_fill_color": "000000", "profile_text_color": "000000", "profile_use_background_image": false, "profile_image_url": "http://pbs.twimg.com/profile_images/1323334867535433728/Sya__NTq_normal.jpg", "profile_image_url_https": "https://pbs.twimg.com/profile_images/1323334867535433728/Sya__NTq_normal.jpg", "profile_banner_url": "https://pbs.twimg.com/profile_banners/1098642312614297600/1555517271", "default_profile": false, "default_profile_image": false, "following": null, "follow_request_sent": null, "notifications": null}, "geo": null, "coordinates": null, "place": null, "contributors": null, "is_quote_status": false, "extended_tweet": {"full_text": "$U priced its IPO of 25M shares at $52 (above the expected price range of $44-48 which was already raised from $34-42). This gives the video game software developer an initial valuation of $13.7B. The company believes the total market for its products and services is $29B.", "display_text_range": [0, 273], "entities": {"hashtags": [], "urls": [], "user_mentions": [], "symbols": [{"text": "U", "indices": [0, 2]}]}}, "quote_count": 0, "reply_count": 1, "retweet_count": 0, "favorite_count": 0, "entities": {"hashtags": [], "urls": [{"url": "https://t.co/DZ0fDZu6YP", "expanded_url": "https://twitter.com/i/web/status/1306917797939884032", "display_url": "twitter.com/i/web/status/1\u2026", "indices": [117, 140]}], "user_mentions": [], "symbols": [{"text": "U", "indices": [0, 2]}]}, "favorited": false, "retweeted": false, "filter_level": "low", "lang": "en", "matching_rules": [{"tag": null}]}