{"created_at": "Fri Sep 18 04:32:32 +0000 2020", "id": 1306813333035724802, "id_str": "1306813333035724802", "text": "RT @dailytradingapp: #eSports #FROG Unity Raises IPO Target To Above $1.8B, Set To Become 4th Tech Listing This Week https://t.co/WZOX10FTm\u2026", "source": "<a href=\"https://rtweeters.com\" rel=\"nofollow\">RtBot4</a>", "truncated": false, "in_reply_to_status_id": null, "in_reply_to_status_id_str": null, "in_reply_to_user_id": null, "in_reply_to_user_id_str": null, "in_reply_to_screen_name": null, "user": {"id": 3180931062, "id_str": "3180931062", "name": "Esports RTs", "screen_name": "EsportsTweeter", "location": "United States", "url": null, "description": "Esports Retweets. Supporting Esports Worldwide!\n@ us for a retweet and Use the hashtag #esports for a retweet.", "translator_type": "none", "protected": false, "verified": false, "followers_count": 2995, "friends_count": 3, "listed_count": 20, "favourites_count": 263, "statuses_count": 82672, "created_at": "Thu Apr 30 20:34:46 +0000 2015", "utc_offset": null, "time_zone": null, "geo_enabled": false, "lang": null, "contributors_enabled": false, "is_translator": false, "profile_background_color": "022330", "profile_background_image_url": "http://abs.twimg.com/images/themes/theme1/bg.png", "profile_background_image_url_https": "https://abs.twimg.com/images/themes/theme1/bg.png", "profile_background_tile": false, "profile_link_color": "0084B4", "profile_sidebar_border_color": "000000", "profile_sidebar_fill_color": "000000", "profile_text_color": "000000", "profile_use_background_image": true, "profile_image_url": "http://pbs.twimg.com/profile_images/1245407487446192128/PLFgxXCW_normal.jpg", "profile_image_url_https": "https://pbs.twimg.com/profile_images/1245407487446192128/PLFgxXCW_normal.jpg", "profile_banner_url": "https://pbs.twimg.com/profile_banners/3180931062/1585763258", "default_profile": false, "default_profile_image": false, "following": null, "follow_request_sent": null, "notifications": null}, "geo": null, "coordinates": null, "place": null, "contributors": null, "retweeted_status": {"created_at": "Fri Sep 18 04:29:32 +0000 2020", "id": 1306812577574313985, "id_str": "1306812577574313985", "text": "#eSports #FROG Unity Raises IPO Target To Above $1.8B, Set To Become 4th Tech Listing This Week\u2026 https://t.co/eCIxKU5gxk", "display_text_range": [0, 140], "source": "<a href=\"https://dlvrit.com/\" rel=\"nofollow\">dlvr.it</a>", "truncated": true, "in_reply_to_status_id": null, "in_reply_to_status_id_str": null, "in_reply_to_user_id": null, "in_reply_to_user_id_str": null, "in_reply_to_screen_name": null, "user": {"id": 1166772455417024512, "id_str": "1166772455417024512", "name": "dailytradingapp", "screen_name": "dailytradingapp", "location": null, "url": "http://www.dailytradingapp.com", "description": "#DayTrading Management Tool\nOrganize your day trading #stocks the easy way, with a quick access, all in one place.\nDownload Today!", "translator_type": "none", "protected": false, "verified": false, "followers_count": 244, "friends_count": 269, "listed_count": 6, "favourites_count": 4, "statuses_count": 16112, "created_at": "Wed Aug 28 18:00:19 +0000 2019", "utc_offset": null, "time_zone": null, "geo_enabled": false, "lang": null, "contributors_enabled": false, "is_translator": false, "profile_background_color": "F5F8FA", "profile_background_image_url": "", "profile_background_image_url_https": "", "profile_background_tile": false, "profile_link_color": "1DA1F2", "profile_sidebar_border_color": "C0DEED", "profile_sidebar_fill_color": "DDEEF6", "profile_text_color": "333333", "profile_use_background_image": true, "profile_image_url": "http://pbs.twimg.com/profile_images/1166993805675048960/l5yma6Q-_normal.jpg", "profile_image_url_https": "https://pbs.twimg.com/profile_images/1166993805675048960/l5yma6Q-_normal.jpg", "profile_banner_url": "https://pbs.twimg.com/profile_banners/1166772455417024512/1577880793", "default_profile": true, "default_profile_image": false, "following": null, "follow_request_sent": null, "notifications": null}, "geo": null, "coordinates": null, "place": null, "contributors": null, "is_quote_status": false, "extended_tweet": {"full_text": "#eSports #FROG Unity Raises IPO Target To Above $1.8B, Set To Become 4th Tech Listing This Week https://t.co/WZOX10FTm1 https://t.co/V1s3B5J9fz", "display_text_range": [0, 119], "entities": {"hashtags": [{"text": "eSports", "indices": [0, 8]}, {"text": "FROG", "indices": [9, 14]}], "urls": [{"url": "https://t.co/WZOX10FTm1", "expanded_url": "http://dlvr.it/RgrVkc", "display_url": "dlvr.it/RgrVkc", "indices": [96, 119]}], "user_mentions": [], "symbols": [], "media": [{"id": 1306812575925952513, "id_str": "1306812575925952513", "indices": [120, 143], "media_url": "http://pbs.twimg.com/media/EiK7HTAUYAEpVt5.jpg", "media_url_https": "https://pbs.twimg.com/media/EiK7HTAUYAEpVt5.jpg", "url": "https://t.co/V1s3B5J9fz", "display_url": "pic.twitter.com/V1s3B5J9fz", "expanded_url": "https://twitter.com/dailytradingapp/status/1306812577574313985/photo/1", "type": "photo", "sizes": {"thumb": {"w": 150, "h": 150, "resize": "crop"}, "medium": {"w": 1200, "h": 630, "resize": "fit"}, "small": {"w": 680, "h": 357, "resize": "fit"}, "large": {"w": 1200, "h": 630, "resize": "fit"}}}]}, "extended_entities": {"media": [{"id": 1306812575925952513, "id_str": "1306812575925952513", "indices": [120, 143], "media_url": "http://pbs.twimg.com/media/EiK7HTAUYAEpVt5.jpg", "media_url_https": "https://pbs.twimg.com/media/EiK7HTAUYAEpVt5.jpg", "url": "https://t.co/V1s3B5J9fz", "display_url": "pic.twitter.com/V1s3B5J9fz", "expanded_url": "https://twitter.com/dailytradingapp/status/1306812577574313985/photo/1", "type": "photo", "sizes": {"thumb": {"w": 150, "h": 150, "resize": "crop"}, "medium": {"w": 1200, "h": 630, "resize": "fit"}, "small": {"w": 680, "h": 357, "resize": "fit"}, "large": {"w": 1200, "h": 630, "resize": "fit"}}}]}}, "quote_count": 0, "reply_count": 0, "retweet_count": 1, "favorite_count": 1, "entities": {"hashtags": [{"text": "eSports", "indices": [0, 8]}, {"text": "FROG", "indices": [9, 14]}], "urls": [{"url": "https://t.co/eCIxKU5gxk", "expanded_url": "https://twitter.com/i/web/status/1306812577574313985", "display_url": "twitter.com/i/web/status/1\u2026", "indices": [97, 120]}], "user_mentions": [], "symbols": []}, "favorited": false, "retweeted": false, "possibly_sensitive": false, "filter_level": "low", "lang": "en"}, "is_quote_status": false, "quote_count": 0, "reply_count": 0, "retweet_count": 0, "favorite_count": 0, "entities": {"hashtags": [{"text": "eSports", "indices": [21, 29]}, {"text": "FROG", "indices": [30, 35]}], "urls": [], "user_mentions": [{"screen_name": "dailytradingapp", "name": "dailytradingapp", "id": 1166772455417024512, "id_str": "1166772455417024512", "indices": [3, 19]}], "symbols": []}, "favorited": false, "retweeted": false, "filter_level": "low", "lang": "en", "matching_rules": [{"tag": null}]}