{"created_at": "Fri Sep 18 01:55:04 +0000 2020", "id": 1306773705696051201, "id_str": "1306773705696051201", "text": "Unity's IPO process tomorrow will be unique in that they will be setting the price / allocations vs. the underwrite\u2026 https://t.co/ld6wba70ft", "source": "<a href=\"https://mobile.twitter.com\" rel=\"nofollow\">Twitter Web App</a>", "truncated": true, "in_reply_to_status_id": null, "in_reply_to_status_id_str": null, "in_reply_to_user_id": null, "in_reply_to_user_id_str": null, "in_reply_to_screen_name": null, "user": {"id": 988881325347262464, "id_str": "988881325347262464", "name": "Benjamin Jang", "screen_name": "benjaminwjang", "location": "San Francisco, CA", "url": null, "description": "Corp Dev @GapInc, former investment banker @Cowen_Inc @JPMorgan / tech & consumer enthusiast / views are my own", "translator_type": "none", "protected": false, "verified": false, "followers_count": 80, "friends_count": 646, "listed_count": 1, "favourites_count": 2195, "statuses_count": 358, "created_at": "Tue Apr 24 20:44:15 +0000 2018", "utc_offset": null, "time_zone": null, "geo_enabled": false, "lang": null, "contributors_enabled": false, "is_translator": false, "profile_background_color": "F5F8FA", "profile_background_image_url": "", "profile_background_image_url_https": "", "profile_background_tile": false, "profile_link_color": "1DA1F2", "profile_sidebar_border_color": "C0DEED", "profile_sidebar_fill_color": "DDEEF6", "profile_text_color": "333333", "profile_use_background_image": true, "profile_image_url": "http://pbs.twimg.com/profile_images/1194157630295461890/KwwW84YN_normal.jpg", "profile_image_url_https": "https://pbs.twimg.com/profile_images/1194157630295461890/KwwW84YN_normal.jpg", "profile_banner_url": "https://pbs.twimg.com/profile_banners/988881325347262464/1573544440", "default_profile": true, "default_profile_image": false, "following": null, "follow_request_sent": null, "notifications": null}, "geo": null, "coordinates": null, "place": null, "contributors": null, "is_quote_status": false, "extended_tweet": {"full_text": "Unity's IPO process tomorrow will be unique in that they will be setting the price / allocations vs. the underwriters. \n\nIf this is done successfully, it could pave a new way for companies to come to market.", "display_text_range": [0, 207], "entities": {"hashtags": [], "urls": [], "user_mentions": [], "symbols": []}}, "quote_count": 0, "reply_count": 0, "retweet_count": 0, "favorite_count": 1, "entities": {"hashtags": [], "urls": [{"url": "https://t.co/ld6wba70ft", "expanded_url": "https://twitter.com/i/web/status/1306773705696051201", "display_url": "twitter.com/i/web/status/1\u2026", "indices": [117, 140]}], "user_mentions": [], "symbols": []}, "favorited": false, "retweeted": false, "filter_level": "low", "lang": "en", "matching_rules": [{"tag": null}]}