{"created_at": "Tue Sep 29 15:34:57 +0000 2020", "id": 1310966301855223808, "id_str": "1310966301855223808", "text": "\u2066@PalantirTech\u2069 #IPO : Surprisingly, Initial Valuations Look Reasonable \u2066@SeekingAlpha\u2069 #technology #Security  https://t.co/NiFzG4lJdg", "source": "<a href=\"http://twitter.com/download/iphone\" rel=\"nofollow\">Twitter for iPhone</a>", "truncated": false, "in_reply_to_status_id": null, "in_reply_to_status_id_str": null, "in_reply_to_user_id": null, "in_reply_to_user_id_str": null, "in_reply_to_screen_name": null, "user": {"id": 50018532, "id_str": "50018532", "name": "Amin Moradi-Talebi\ud83d\udee2\ud83d\udd0b", "screen_name": "AMoradiTalebi", "location": null, "url": null, "description": "Interested #technology Bkgrd: MBA - Trade Finance - Engineer Telecom UNIGE HEPIA #OOTT #fintech #AI \ud83d\udcbb\ud83d\udc7b\ud83d\udc23\ud83d\udd78\ud83d\udc7e\ud83d\udee2", "translator_type": "none", "protected": false, "verified": false, "followers_count": 227, "friends_count": 1415, "listed_count": 67, "favourites_count": 1904, "statuses_count": 13615, "created_at": "Tue Jun 23 16:12:39 +0000 2009", "utc_offset": null, "time_zone": null, "geo_enabled": true, "lang": null, "contributors_enabled": false, "is_translator": false, "profile_background_color": "C0DEED", "profile_background_image_url": "http://abs.twimg.com/images/themes/theme1/bg.png", "profile_background_image_url_https": "https://abs.twimg.com/images/themes/theme1/bg.png", "profile_background_tile": false, "profile_link_color": "0084B4", "profile_sidebar_border_color": "C0DEED", "profile_sidebar_fill_color": "DDEEF6", "profile_text_color": "333333", "profile_use_background_image": true, "profile_image_url": "http://pbs.twimg.com/profile_images/1246185536668213249/HjxUyD9t_normal.jpg", "profile_image_url_https": "https://pbs.twimg.com/profile_images/1246185536668213249/HjxUyD9t_normal.jpg", "profile_banner_url": "https://pbs.twimg.com/profile_banners/50018532/1566511957", "default_profile": false, "default_profile_image": false, "following": null, "follow_request_sent": null, "notifications": null}, "geo": null, "coordinates": null, "place": null, "contributors": null, "is_quote_status": false, "quote_count": 0, "reply_count": 0, "retweet_count": 0, "favorite_count": 0, "entities": {"hashtags": [{"text": "IPO", "indices": [16, 20]}, {"text": "technology", "indices": [88, 99]}, {"text": "Security", "indices": [100, 109]}], "urls": [{"url": "https://t.co/NiFzG4lJdg", "expanded_url": "https://seekingalpha.com/article/4376812-palantir-ipo-surprisingly-initial-valuations-look-reasonable", "display_url": "seekingalpha.com/article/437681\u2026", "indices": [111, 134]}], "user_mentions": [{"screen_name": "PalantirTech", "name": "Palantir", "id": 37959591, "id_str": "37959591", "indices": [1, 14]}, {"screen_name": "SeekingAlpha", "name": "Seeking Alpha", "id": 23059499, "id_str": "23059499", "indices": [73, 86]}], "symbols": []}, "favorited": false, "retweeted": false, "possibly_sensitive": false, "filter_level": "low", "lang": "en", "matching_rules": [{"tag": null}]}