{"created_at": "Wed Sep 16 12:26:40 +0000 2020", "id": 1306207874293608450, "id_str": "1306207874293608450", "text": "Tminus 65 minutes for SNOW ipo. Good luck all.", "source": "<a href=\"http://twitter.com/download/android\" rel=\"nofollow\">Twitter for Android</a>", "truncated": false, "in_reply_to_status_id": null, "in_reply_to_status_id_str": null, "in_reply_to_user_id": null, "in_reply_to_user_id_str": null, "in_reply_to_screen_name": null, "user": {"id": 723634071872495616, "id_str": "723634071872495616", "name": "Lushy Lluun", "screen_name": "LushyLluun", "location": "Midgar", "url": null, "description": "day trader, cad designer, will never get a fall guys crown", "translator_type": "none", "protected": false, "verified": false, "followers_count": 58, "friends_count": 272, "listed_count": 0, "favourites_count": 1348, "statuses_count": 4989, "created_at": "Fri Apr 22 22:06:22 +0000 2016", "utc_offset": null, "time_zone": null, "geo_enabled": false, "lang": null, "contributors_enabled": false, "is_translator": false, "profile_background_color": "F5F8FA", "profile_background_image_url": "", "profile_background_image_url_https": "", "profile_background_tile": false, "profile_link_color": "1DA1F2", "profile_sidebar_border_color": "C0DEED", "profile_sidebar_fill_color": "DDEEF6", "profile_text_color": "333333", "profile_use_background_image": true, "profile_image_url": "http://pbs.twimg.com/profile_images/1310705004626489345/GMuEnVwA_normal.jpg", "profile_image_url_https": "https://pbs.twimg.com/profile_images/1310705004626489345/GMuEnVwA_normal.jpg", "profile_banner_url": "https://pbs.twimg.com/profile_banners/723634071872495616/1595593714", "default_profile": true, "default_profile_image": false, "following": null, "follow_request_sent": null, "notifications": null}, "geo": null, "coordinates": null, "place": null, "contributors": null, "is_quote_status": false, "quote_count": 0, "reply_count": 0, "retweet_count": 0, "favorite_count": 0, "entities": {"hashtags": [], "urls": [], "user_mentions": [], "symbols": []}, "favorited": false, "retweeted": false, "filter_level": "low", "lang": "en", "matching_rules": [{"tag": null}]}