{"created_at": "Mon Sep 28 01:24:32 +0000 2020", "id": 1310389899644686337, "id_str": "1310389899644686337", "text": "IPO mania: Snowflake, Ant, Plantir, Asana and many more..This week is a big test for the IPO market\n\nhttps://t.co/KPwNGkysBe", "source": "<a href=\"http://twitter.com/download/android\" rel=\"nofollow\">Twitter for Android</a>", "truncated": false, "in_reply_to_status_id": null, "in_reply_to_status_id_str": null, "in_reply_to_user_id": null, "in_reply_to_user_id_str": null, "in_reply_to_screen_name": null, "user": {"id": 400172392, "id_str": "400172392", "name": "Rasitha W", "screen_name": "rasithaw", "location": "Sri Lanka", "url": "https://www.linkedin.com/in/rasithaw/", "description": "Passionate about helping businesses to 'Run & Re-invent' and creating a happy, prosperous Sri Lanka, enabled by TEA! (Transparency, Equality & Accoutability)", "translator_type": "none", "protected": false, "verified": false, "followers_count": 76, "friends_count": 157, "listed_count": 15, "favourites_count": 430, "statuses_count": 3425, "created_at": "Fri Oct 28 16:20:11 +0000 2011", "utc_offset": null, "time_zone": null, "geo_enabled": true, "lang": null, "contributors_enabled": false, "is_translator": false, "profile_background_color": "C0DEED", "profile_background_image_url": "http://abs.twimg.com/images/themes/theme1/bg.png", "profile_background_image_url_https": "https://abs.twimg.com/images/themes/theme1/bg.png", "profile_background_tile": false, "profile_link_color": "1DA1F2", "profile_sidebar_border_color": "C0DEED", "profile_sidebar_fill_color": "DDEEF6", "profile_text_color": "333333", "profile_use_background_image": true, "profile_image_url": "http://pbs.twimg.com/profile_images/2647816594/7f8480cae4836dcfbccdd8b0fc51a8ac_normal.jpeg", "profile_image_url_https": "https://pbs.twimg.com/profile_images/2647816594/7f8480cae4836dcfbccdd8b0fc51a8ac_normal.jpeg", "default_profile": true, "default_profile_image": false, "following": null, "follow_request_sent": null, "notifications": null}, "geo": null, "coordinates": null, "place": {"id": "173c2bb9d42baaa5", "url": "https://api.twitter.com/1.1/geo/id/173c2bb9d42baaa5.json", "place_type": "country", "name": "Sri Lanka", "full_name": "Sri Lanka", "country_code": "LK", "country": "Sri Lanka", "bounding_box": {"type": "Polygon", "coordinates": [[[79.650526, 5.921383], [79.650526, 9.835938], [81.878782, 9.835938], [81.878782, 5.921383]]]}, "attributes": {}}, "contributors": null, "is_quote_status": false, "quote_count": 0, "reply_count": 0, "retweet_count": 0, "favorite_count": 0, "entities": {"hashtags": [], "urls": [{"url": "https://t.co/KPwNGkysBe", "expanded_url": "https://www.cnn.com/2020/09/27/investing/stocks-week-ahead/index.html", "display_url": "cnn.com/2020/09/27/inv\u2026", "indices": [101, 124]}], "user_mentions": [], "symbols": []}, "favorited": false, "retweeted": false, "possibly_sensitive": false, "filter_level": "low", "lang": "en", "matching_rules": [{"tag": null}]}